odoo/addons/sale_exception_holidays_public/README.rst
odoo/addons/sale_exception_holidays_public/__init__.py
odoo/addons/sale_exception_holidays_public/__manifest__.py
odoo/addons/sale_exception_holidays_public/data/sale_exception_data.xml
odoo/addons/sale_exception_holidays_public/i18n/es.po
odoo/addons/sale_exception_holidays_public/i18n/fr.po
odoo/addons/sale_exception_holidays_public/i18n/it.po
odoo/addons/sale_exception_holidays_public/i18n/sale_exception_holidays_public.pot
odoo/addons/sale_exception_holidays_public/models/__init__.py
odoo/addons/sale_exception_holidays_public/models/sale_order.py
odoo/addons/sale_exception_holidays_public/readme/CONFIGURE.md
odoo/addons/sale_exception_holidays_public/readme/CONTRIBUTORS.md
odoo/addons/sale_exception_holidays_public/readme/CREDITS.md
odoo/addons/sale_exception_holidays_public/readme/DESCRIPTION.md
odoo/addons/sale_exception_holidays_public/readme/USAGE.md
odoo/addons/sale_exception_holidays_public/static/description/icon.png
odoo/addons/sale_exception_holidays_public/static/description/index.html
odoo/addons/sale_exception_holidays_public/tests/__init__.py
odoo/addons/sale_exception_holidays_public/tests/test_sale_exception.py
odoo_addon_sale_exception_holidays_public-17.0.1.0.0.2.dist-info/METADATA
odoo_addon_sale_exception_holidays_public-17.0.1.0.0.2.dist-info/WHEEL
odoo_addon_sale_exception_holidays_public-17.0.1.0.0.2.dist-info/top_level.txt
odoo_addon_sale_exception_holidays_public-17.0.1.0.0.2.dist-info/RECORD
