Metadata-Version: 2.1
Name: odoo-addon-sale_exception_holidays_public
Version: 17.0.1.0.0.2
Requires-Python: >=3.10
Requires-Dist: odoo-addon-hr_holidays_public>=17.0dev,<17.1dev
Requires-Dist: odoo-addon-sale_exception>=17.0dev,<17.1dev
Requires-Dist: odoo>=17.0a,<17.1dev
Summary: Raise a sale exception if there is a commitment_date on the SO and this date is a public holidays for the shipping partner address
Home-page: https://github.com/OCA/sale-workflow
License: AGPL-3
Author: Camptocamp, BCIM, Odoo Community Association (OCA)
Author-email: support@odoo-community.org
Classifier: Programming Language :: Python
Classifier: Framework :: Odoo
Classifier: Framework :: Odoo :: 17.0
Classifier: License :: OSI Approved :: GNU Affero General Public License v3
